{"name":"URL","identifier":"DVVQZ2EMBV","description":null,"slotTypeValues":[{"synonyms":null,"sampleValue":{"value":"https://grupo3-teste.slack.com/files/"}},{"synonyms":null,"sampleValue":{"value":"https://grupo3-teste.slack.com/files/U052VEWC0S0/F053GMGDN80/baby_madonna.jpg"}},{"synonyms":null,"sampleValue":{"value":"https://files.slack.com/files-pri/T053GM49M4G-F052HDY1U31/baby_madonna.jpg"}},{"synonyms":null,"sampleValue":{"value":"https://files.slack.com/files-pri/"}}],"parentSlotTypeSignature":null,"valueSelectionSetting":{"regexFilter":null,"resolutionStrategy":"ORIGINAL_VALUE"}}